prp/__init__.py
prp/main.py
xiaobai_prp-1.0.15.dist-info/METADATA
xiaobai_prp-1.0.15.dist-info/WHEEL
xiaobai_prp-1.0.15.dist-info/entry_points.txt
xiaobai_prp-1.0.15.dist-info/top_level.txt
xiaobai_prp-1.0.15.dist-info/RECORD
