Metadata-Version: 2.4
Name: xiaobai-prp
Version: 1.0.15
Summary: Python Registry Provider - A tool for managing Python package index sources similar to nrm for npm
Home-page: https://github.com/xiaobaiOTS/xiaobai-prp
Author: Tser
Author-email: Tser <807447312@qq.com>
License: GPL-3.0
Project-URL: Homepage, https://github.com/xiaobaiOTS/xiaobai-prp
Project-URL: Repository, https://github.com/xiaobaiOTS/xiaobai-prp
Classifier: Development Status :: 4 - Beta
Classifier: Intended Audience :: Developers
Classifier: License :: OSI Approved :: GNU General Public License v3 (GPLv3)
Classifier: Operating System :: OS Independent
Classifier: Programming Language :: Python :: 3
Classifier: Programming Language :: Python :: 3.7
Classifier: Programming Language :: Python :: 3.8
Classifier: Programming Language :: Python :: 3.9
Classifier: Programming Language :: Python :: 3.10
Classifier: Programming Language :: Python :: 3.11
Classifier: Topic :: Software Development :: Libraries :: Python Modules
Requires-Python: >=3.8
Dynamic: author
Dynamic: home-page
Dynamic: requires-python
